[
  {
    "id": "Something",
    "longname": "Something",
    "name": "Something",
    "scope": "global",
    "kind": "class",
    "description": "something",
    "meta": {
      "lineno": 6,
      "filename": "0-src.js",
      "path": "/Users/lloydb/Documents/jsdoc2md/testbed/build/jsdoc/global/scope-inner-es6"
    },
    "order": 0
  },
  {
    "id": "<anonymous>~four",
    "longname": "<anonymous>~four",
    "name": "four",
    "scope": "inner",
    "kind": "member",
    "description": "inner var",
    "memberof": "<anonymous>",
    "meta": {
      "lineno": 16,
      "filename": "0-src.js",
      "path": "/Users/lloydb/Documents/jsdoc2md/testbed/build/jsdoc/global/scope-inner-es6"
    },
    "order": 2
  },
  {
    "id": "<anonymous>~three",
    "longname": "<anonymous>~three",
    "name": "three",
    "scope": "inner",
    "kind": "constant",
    "description": "inner constant",
    "memberof": "<anonymous>",
    "meta": {
      "lineno": 11,
      "filename": "0-src.js",
      "path": "/Users/lloydb/Documents/jsdoc2md/testbed/build/jsdoc/global/scope-inner-es6"
    },
    "order": 1
  }
]
