[
  {
    "comment": "/** @namespace */",
    "meta": {
      "range": [
        22,
        145
      ],
      "filename": "0-src.js",
      "lineno": 2,
      "path": "/Users/lloyd/Documents/jsdoc2md/testbed/build/global/private",
      "code": {
        "id": "astnode100000002",
        "name": "Documents",
        "type": "ObjectExpression",
        "value": "{\"Newspaper\":1,\"Diary\":2}"
      }
    },
    "kind": "namespace",
    "name": "Documents",
    "longname": "Documents",
    "scope": "global"
  },
  {
    "comment": "/**\n   * An ordinary newspaper.\n   */",
    "meta": {
      "range": [
        78,
        90
      ],
      "filename": "0-src.js",
      "lineno": 6,
      "path": "/Users/lloyd/Documents/jsdoc2md/testbed/build/global/private",
      "code": {
        "id": "astnode100000005",
        "name": "Newspaper",
        "type": "Literal",
        "value": 1
      }
    },
    "description": "An ordinary newspaper.",
    "name": "Newspaper",
    "longname": "Documents.Newspaper",
    "kind": "member",
    "memberof": "Documents",
    "scope": "static"
  },
  {
    "comment": "/**\n   * My diary.\n   * @private\n   */",
    "meta": {
      "range": [
        135,
        143
      ],
      "filename": "0-src.js",
      "lineno": 11,
      "path": "/Users/lloyd/Documents/jsdoc2md/testbed/build/global/private",
      "code": {
        "id": "astnode100000007",
        "name": "Diary",
        "type": "Literal",
        "value": 2
      }
    },
    "description": "My diary.",
    "access": "private",
    "name": "Diary",
    "longname": "Documents.Diary",
    "kind": "member",
    "memberof": "Documents",
    "scope": "static"
  },
  {
    "kind": "package",
    "longname": "package:undefined",
    "files": [
      "/Users/lloyd/Documents/jsdoc2md/testbed/build/global/private/0-src.js"
    ]
  }
]