[
  {
    "id": "Synth",
    "longname": "Synth",
    "name": "Synth",
    "scope": "global",
    "kind": "class",
    "implements": [
      "Speech"
    ],
    "description": "a synth, that also implements speech",
    "meta": {
      "lineno": 6,
      "filename": "0-src.js",
      "path": "/Users/lloydb/Documents/jsdoc2md/testbed/build/jsdoc/global/implements"
    },
    "order": 0
  },
  {
    "id": "Synth#demo",
    "longname": "Synth#demo",
    "name": "demo",
    "scope": "instance",
    "kind": "function",
    "description": "play a demo piece, Beethoven or something..",
    "memberof": "Synth",
    "meta": {
      "lineno": 10,
      "filename": "0-src.js",
      "path": "/Users/lloydb/Documents/jsdoc2md/testbed/build/jsdoc/global/implements"
    },
    "order": 1
  }
]
