[
  {
    "id": "module:animal",
    "longname": "module:animal",
    "name": "animal",
    "kind": "module",
    "description": "Animals are multicellular, eukaryotic organisms of the kingdom Animalia (also called Metazoa). Their body plan eventually becomes fixed as they develop, although some undergo a process of metamorphosis later on in their lives. Most animals are motile, meaning they can move spontaneously and independently. All animals must ingest other organisms or their products for sustenance (see Heterotroph).\n\n| yeah | desc |\n| ---- | ---- |\n| some | markdown |\n| in the | module |\n| description | |",
    "examples": [
      "var animal = require(\"animal\")"
    ],
    "meta": {
      "lineno": 1,
      "filename": "animal.js",
      "path": "/Users/lloydb/Documents/jsdoc2md/testbed/build/jsdoc2md/dmd-options/module-index-format/src"
    },
    "order": 0
  },
  {
    "id": "module:builder",
    "longname": "module:builder",
    "name": "builder",
    "kind": "module",
    "description": "Aside from humans, who are the most prolific and versatile builders, building behaviour is common in many mammals, birds, insects and arachnids. It is also seen in a few species of fish, reptiles, amphibians, molluscs, urochordates, crustaceans, annelids and some other arthropods. It is virtually absent from all the other animal phyla.",
    "meta": {
      "lineno": 1,
      "filename": "builder.js",
      "path": "/Users/lloydb/Documents/jsdoc2md/testbed/build/jsdoc2md/dmd-options/module-index-format/src"
    },
    "order": 6
  },
  {
    "id": "module:species",
    "longname": "module:species",
    "name": "species",
    "kind": "module",
    "description": "In biology, a species (abbreviated sp., with the plural form species abbreviated spp.) is one of the basic units of biological classification and a taxonomic rank. A species is often defined as the largest group of organisms capable of interbreeding and producing fertile offspring. While in many cases this definition is adequate, the difficulty of defining species is known as the species problem. Differing measures are often used, such as similarity of DNA, morphology, or ecological niche. Presence of specific locally adapted traits may further subdivide species into \"infraspecific taxa\" such as subspecies (and in botany other taxa are used, such as varieties, subvarieties, and formae).",
    "meta": {
      "lineno": 1,
      "filename": "species.js",
      "path": "/Users/lloydb/Documents/jsdoc2md/testbed/build/jsdoc2md/dmd-options/module-index-format/src"
    },
    "order": 10
  },
  {
    "id": "module:animal~Animal()",
    "longname": "module:animal~Animal",
    "name": "Animal",
    "kind": "constructor",
    "memberof": "module:animal~Animal",
    "params": [
      {
        "type": {
          "names": [
            "array"
          ]
        },
        "description": "an array of two parent {@link Animal} objects",
        "name": "species"
      },
      {
        "type": {
          "names": [
            "Species"
          ]
        },
        "description": "the species",
        "name": "parents"
      }
    ],
    "order": 2
  },
  {
    "id": "module:animal~Animal#age",
    "longname": "module:animal~Animal#age",
    "name": "age",
    "scope": "instance",
    "kind": "member",
    "description": "the current age",
    "memberof": "module:animal~Animal",
    "type": {
      "names": [
        "number"
      ]
    },
    "defaultvalue": "0",
    "meta": {
      "lineno": 27,
      "filename": "animal.js",
      "path": "/Users/lloydb/Documents/jsdoc2md/testbed/build/jsdoc2md/dmd-options/module-index-format/src"
    },
    "order": 3
  },
  {
    "id": "module:animal~Animal#species",
    "longname": "module:animal~Animal#species",
    "name": "species",
    "scope": "instance",
    "kind": "member",
    "memberof": "module:animal~Animal",
    "type": {
      "names": [
        "Species"
      ]
    },
    "meta": {
      "lineno": 32,
      "filename": "animal.js",
      "path": "/Users/lloydb/Documents/jsdoc2md/testbed/build/jsdoc2md/dmd-options/module-index-format/src"
    },
    "order": 4
  },
  {
    "id": "module:species~Species#name",
    "longname": "module:species~Species#name",
    "name": "name",
    "scope": "instance",
    "kind": "member",
    "description": "the species name",
    "memberof": "module:species~Species",
    "type": {
      "names": [
        "string"
      ]
    },
    "meta": {
      "lineno": 16,
      "filename": "species.js",
      "path": "/Users/lloydb/Documents/jsdoc2md/testbed/build/jsdoc2md/dmd-options/module-index-format/src"
    },
    "order": 12
  },
  {
    "id": "module:species~Species#species",
    "longname": "module:species~Species#species",
    "name": "species",
    "scope": "instance",
    "kind": "member",
    "memberof": "module:species~Species",
    "type": {
      "names": [
        "Species"
      ]
    },
    "meta": {
      "lineno": 21,
      "filename": "species.js",
      "path": "/Users/lloydb/Documents/jsdoc2md/testbed/build/jsdoc2md/dmd-options/module-index-format/src"
    },
    "order": 13
  },
  {
    "id": "module:animal~Animal.eMood",
    "longname": "module:animal~Animal.eMood",
    "name": "eMood",
    "scope": "static",
    "kind": "member",
    "description": "Animal moods",
    "memberof": "module:animal~Animal",
    "isEnum": true,
    "properties": [
      {
        "description": "chilling",
        "name": "satisfied",
        "longname": "module:animal~Animal.eMood.satisfied",
        "kind": "member",
        "memberof": "module:animal~Animal.eMood",
        "scope": "static",
        "defaultvalue": 0
      },
      {
        "description": "pissed off",
        "name": "angry",
        "longname": "module:animal~Animal.eMood.angry",
        "kind": "member",
        "memberof": "module:animal~Animal.eMood",
        "scope": "static",
        "defaultvalue": 1
      },
      {
        "description": "need to eat",
        "name": "hungry",
        "longname": "module:animal~Animal.eMood.hungry",
        "kind": "member",
        "memberof": "module:animal~Animal.eMood",
        "scope": "static",
        "defaultvalue": 2
      }
    ],
    "meta": {
      "lineno": 39,
      "filename": "animal.js",
      "path": "/Users/lloydb/Documents/jsdoc2md/testbed/build/jsdoc2md/dmd-options/module-index-format/src"
    },
    "order": 5
  },
  {
    "id": "module:builder~builder.construct",
    "longname": "module:builder~builder.construct",
    "name": "construct",
    "scope": "static",
    "kind": "function",
    "description": "construct something",
    "memberof": "module:builder~builder",
    "meta": {
      "lineno": 13,
      "filename": "builder.js",
      "path": "/Users/lloydb/Documents/jsdoc2md/testbed/build/jsdoc2md/dmd-options/module-index-format/src"
    },
    "order": 8
  },
  {
    "id": "module:builder~builder.repair",
    "longname": "module:builder~builder.repair",
    "name": "repair",
    "scope": "static",
    "kind": "function",
    "description": "repair something",
    "memberof": "module:builder~builder",
    "meta": {
      "lineno": 17,
      "filename": "builder.js",
      "path": "/Users/lloydb/Documents/jsdoc2md/testbed/build/jsdoc2md/dmd-options/module-index-format/src"
    },
    "order": 9
  },
  {
    "id": "module:species~Species.merge",
    "longname": "module:species~Species.merge",
    "name": "merge",
    "scope": "static",
    "kind": "function",
    "description": "merge two species into a new one",
    "memberof": "module:species~Species",
    "params": [
      {
        "type": {
          "names": [
            "Species"
          ]
        },
        "description": "first",
        "name": "one"
      },
      {
        "type": {
          "names": [
            "Species"
          ]
        },
        "description": "second",
        "name": "two"
      }
    ],
    "returns": [
      {
        "type": {
          "names": [
            "Species"
          ]
        }
      }
    ],
    "meta": {
      "lineno": 30,
      "filename": "species.js",
      "path": "/Users/lloydb/Documents/jsdoc2md/testbed/build/jsdoc2md/dmd-options/module-index-format/src"
    },
    "order": 14
  },
  {
    "id": "module:animal~Animal",
    "longname": "module:animal~Animal",
    "name": "Animal",
    "scope": "inner",
    "kind": "class",
    "memberof": "module:animal",
    "meta": {
      "lineno": 21,
      "filename": "animal.js",
      "path": "/Users/lloydb/Documents/jsdoc2md/testbed/build/jsdoc2md/dmd-options/module-index-format/src"
    },
    "order": 1
  },
  {
    "id": "module:species~Species",
    "longname": "module:species~Species",
    "name": "Species",
    "scope": "inner",
    "kind": "class",
    "memberof": "module:species",
    "meta": {
      "lineno": 11,
      "filename": "species.js",
      "path": "/Users/lloydb/Documents/jsdoc2md/testbed/build/jsdoc2md/dmd-options/module-index-format/src"
    },
    "order": 11
  },
  {
    "id": "module:builder~builder",
    "longname": "module:builder~builder",
    "name": "builder",
    "scope": "inner",
    "kind": "mixin",
    "memberof": "module:builder",
    "meta": {
      "lineno": 9,
      "filename": "builder.js",
      "path": "/Users/lloydb/Documents/jsdoc2md/testbed/build/jsdoc2md/dmd-options/module-index-format/src"
    },
    "order": 7
  }
]
